Metadata-Version: 1.0
Name: djaml
Version: 1.1
Summary: A Django template loader for loading and converting HamlPy markup to HTML
Home-page: http://github.com/chartjes/djaml/
Author: Chris Hartjes
Author-email: UNKNOWN
License: MIT
Keywords: django haml hamlpy
Platform: UNKNOWN
Classifier: License :: OSI Approved :: MIT License
Classifier: Programming Language :: Python
Classifier: Environment :: Web Environment
Classifier: Intended Audience :: Developers
Classifier: Operating System :: OS Independent
Classifier: Topic :: Internet :: WWW/HTTP
Classifier: Topic :: Utilities
